Metadata-Version: 1.1
Name: SimpleCalc2
Version: 0.0.3
Summary: A very basic calculator for algebra problems.
Home-page: UNKNOWN
Author: Leonardo Ricci Mingani
Author-email: leonardo.riccimingani@gmail.com
License: UNKNOWN
Platform: UNKNOWN
Classifier: Development Status :: 5 - Production/Stable
Classifier: Intended Audience :: Developers
Classifier: Operating System :: Microsoft :: Windows :: Windows 10
Classifier: License :: OSI Approved :: MIT License
Classifier: Programming Language :: Python :: 3
